setup.py
coredocs/__init__.py
coredocs/highlighting.py
coredocs/main.py
coredocs/render_markdown.py
coredocs/utils.py
coredocs.egg-info/PKG-INFO
coredocs.egg-info/SOURCES.txt
coredocs.egg-info/dependency_links.txt
coredocs.egg-info/entry_points.txt
coredocs.egg-info/requires.txt
coredocs.egg-info/top_level.txt
coredocs/themes/base/templates/document.html
coredocs/themes/base/templates/link.html
coredocs/themes/base/templates/section.html
coredocs/themes/base/templates/languages/javascript.html
coredocs/themes/base/templates/languages/python.html
coredocs/themes/base/templates/languages/shell.html
coredocs/themes/cerulean/static/css/base.css
coredocs/themes/cerulean/static/css/bootstrap-custom.min.css
coredocs/themes/cerulean/static/css/font-awesome-4.0.3.css
coredocs/themes/cerulean/static/css/highlight.css
coredocs/themes/cerulean/static/fonts/fontawesome-webfont.eot
coredocs/themes/cerulean/static/fonts/fontawesome-webfont.svg
coredocs/themes/cerulean/static/fonts/fontawesome-webfont.ttf
coredocs/themes/cerulean/static/fonts/fontawesome-webfont.woff
coredocs/themes/cerulean/static/img/favicon.ico
coredocs/themes/cerulean/static/img/grid.png
coredocs/themes/cerulean/static/js/base.js
coredocs/themes/cerulean/static/js/bootstrap-3.0.3.min.js
coredocs/themes/cerulean/static/js/highlight.pack.js
coredocs/themes/cerulean/static/js/jquery-1.10.2.min.js
coredocs/themes/cerulean/templates/404.html
coredocs/themes/cerulean/templates/document.html
coredocs/themes/cerulean/templates/index.html
coredocs/themes/cerulean/templates/link.html
coredocs/themes/cerulean/templates/nav.html
coredocs/themes/cerulean/templates/toc.html
coredocs/themes/slate/static/fonts/slate.eot
coredocs/themes/slate/static/fonts/slate.svg
coredocs/themes/slate/static/fonts/slate.ttf
coredocs/themes/slate/static/fonts/slate.woff
coredocs/themes/slate/static/fonts/slate.woff2
coredocs/themes/slate/static/images/logo.png
coredocs/themes/slate/static/images/navbar.png
coredocs/themes/slate/static/javascripts/all.js
coredocs/themes/slate/static/javascripts/all_nosearch.js
coredocs/themes/slate/static/stylesheets/print.css
coredocs/themes/slate/static/stylesheets/screen.css
