Metadata-Version: 1.1
Name: coredocs
Version: 0.0.6
Summary: API documentation generator.
Home-page: http://github.com/core-api/coredocs/
Author: Tom Christie
Author-email: tom@tomchristie.com
License: BSD
Platform: UNKNOWN
Classifier: Intended Audience :: Developers
Classifier: License :: OSI Approved :: BSD License
Classifier: Operating System :: OS Independent
Classifier: Programming Language :: Python
Classifier: Programming Language :: Python :: 3
